sqlexpress/__init__.py
sqlexpress/__main__.py
sqlexpress/exceptions.py
sqlexpress/helpers.py
sqlexpress/graph/__init__.py
sqlexpress/graph/entities.py
sqlexpress/graph/relationships.py
sqlexpress/parsers/__init__.py
sqlexpress/parsers/query.py
sqlexpress/parsers/yaml.py
sqlexpress/structures/__init__.py
sqlexpress/structures/basics.py
sqlexpress/structures/clauses.py
sqlexpress/web/__init__.py
sqlexpress/web/utils.py
sqlexpress/web/views.py
sqlexpress/web/static/css/base.css
sqlexpress/web/static/css/graph.css
sqlexpress/web/static/js/graph.js
sqlexpress/web/static/js/project.js
sqlexpress/web/templates/base.html
sqlexpress/web/templates/home.html
sqlexpress/web/templates/project.html
sqlexpress/web/templates/project_graph.html
sqlexpress/web/templates/project_input.html
sqlexpress/web/templates/project_output.html
sqlexpress/web/templates/project_tables.html
sqlexpress-0.2.4.dist-info/LICENSE.txt
sqlexpress-0.2.4.dist-info/METADATA
sqlexpress-0.2.4.dist-info/WHEEL
sqlexpress-0.2.4.dist-info/top_level.txt
sqlexpress-0.2.4.dist-info/RECORD
