Metadata-Version: 2.1
Name: sqlexpress
Version: 0.2.4
Summary: Package to parse SQL scripts for information
Home-page: https://github.com/sssiong/sqlexpress
Author: sssiong
License: UNKNOWN
Platform: UNKNOWN
License-File: LICENSE.txt
Requires-Dist: networkx (==2.8)
Requires-Dist: PyYAML (==6.0)
Provides-Extra: web
Requires-Dist: Flask (==2.1.2) ; extra == 'web'
